setup.py
django_autocomplete/__init__.py
django_autocomplete/models.py
django_autocomplete/urls.py
django_autocomplete/views.py
django_autocomplete/widgets.py
django_autocomplete_x.egg-info/PKG-INFO
django_autocomplete_x.egg-info/SOURCES.txt
django_autocomplete_x.egg-info/dependency_links.txt
django_autocomplete_x.egg-info/not-zip-safe
django_autocomplete_x.egg-info/top_level.txt
test_auto/__init__.py
test_auto/admin.py
test_auto/apps.py
test_auto/forms.py
test_auto/models.py
test_auto/settings.py
test_auto/tests.py
test_auto/urls.py
test_auto/views.py
test_auto/wsgi.py
test_auto/migrations/0001_initial.py
test_auto/migrations/0002_mymodel2.py
test_auto/migrations/0003_mymodel_ref.py
test_auto/migrations/__init__.py