Metadata-Version: 1.0
Name: django-autocomplete-x
Version: 0.0.5
Summary: django autocomplete plugin
Home-page: https://github.com/exildev/django-autocomplete
Author: Luis Miguel Morales Pajaro
Author-email: luismiguel.mopa@gmail.com
License: Creative Common
Platform: UNKNOWN
